atmos_sci/__init__.py
atmos_sci/atmos_refractivity.py
atmos_sci/met_analysis.py
atmos_sci/mplnet.py
atmos_sci/pbl_lidar.py
atmos_sci/radiosonde.py
fiber_bragg_gratings/__init__.py
fiber_bragg_gratings/fbg_analysis.py
fluid_mechanics/__init__.py
fluid_mechanics/turbulence.py
geo/__init__.py
geo/cartography.py
geo/geotiff.py
numerical_analysis/__init__.py
numerical_analysis/ode.py
plotting/__init__.py
plotting/plotting.py
signal_processing/__init__.py
signal_processing/image_analysis.py
signal_processing/pycuda_fourier.py
signal_processing/pycuda_wavelets.py
signal_processing/signal_analysis.py
signal_processing/wavelets.py
PyKeller-0.0.1.dist-info/LICENSE
PyKeller-0.0.1.dist-info/METADATA
PyKeller-0.0.1.dist-info/WHEEL
PyKeller-0.0.1.dist-info/top_level.txt
PyKeller-0.0.1.dist-info/RECORD
