Metadata-Version: 2.1
Name: PyKeller
Version: 0.0.1
Summary: This package contains the classes and functions used for my research and engineering.
Home-page: https://github.com/dkllrjr/PyKeller
Author: Doug Keller
Author-email: dg.kllr.jr@gmail.com
License: UNKNOWN
Platform: UNKNOWN
Classifier: Programming Language :: Python :: 3
Classifier: License :: OSI Approved :: MIT License
Classifier: Operating System :: OS Independent
